reverse_proxy_send_file/__init__.py
reverse_proxy_send_file/response.py
reverse_proxy_send_file/settings.py
reverse_proxy_send_file/storage.py
reverse_proxy_send_file/url.py
reverse_proxy_send_file/views.py
django_reverse_proxy_send_file-2.0.0.dist-info/METADATA
django_reverse_proxy_send_file-2.0.0.dist-info/WHEEL
django_reverse_proxy_send_file-2.0.0.dist-info/RECORD
