Metadata-Version: 2.1
Name: django-reverse-proxy-send-file
Version: 2.0.0
Summary: Storage and View to send X-Accel-Redirect (or X-Sendfile) header to nginx (or apache) reverse-proxy
Home-page: https://bitbucket.org/hespul/django-reverse-proxy-send-file
License: WTFPL
Author: Fabs
Author-email: fabien.michel@hespul.org
Requires-Python: >=3.8
Classifier: Development Status :: 5 - Production/Stable
Classifier: Environment :: Web Environment
Classifier: Framework :: Django
Classifier: Framework :: Django :: 3.2
Classifier: Framework :: Django :: 4.0
Classifier: Framework :: Django :: 4.1
Classifier: Framework :: Django :: 4.2
Classifier: Framework :: Django :: 5.0
Classifier: Framework :: Django :: 5.1
Classifier: Intended Audience :: Developers
Classifier: License :: Other/Proprietary License
Classifier: License :: Public Domain
Classifier: Operating System :: OS Independent
Classifier: Programming Language :: Python
Classifier: Programming Language :: Python :: 3
Classifier: Programming Language :: Python :: 3.8
Classifier: Programming Language :: Python :: 3.9
Classifier: Programming Language :: Python :: 3.10
Classifier: Programming Language :: Python :: 3.11
Classifier: Programming Language :: Python :: 3.12
Classifier: Programming Language :: Python :: 3.13
Project-URL: Repository, https://bitbucket.org/hespul/django-reverse-proxy-send-file
